{
    "_links": {
        "self": {
            "href": "http:\/\/default\/user\/4?_format=hal_json"
        },
        "type": {
            "href": "http:\/\/drupal.org\/rest\/type\/user\/user"
        }
    },
    "uid": [
        {
            "value": 4
        }
    ],
    "uuid": [
        {
            "value": "47a495d2-d150-40bf-bea6-ba558e1bdaa2"
        }
    ],
    "langcode": [
        {
            "value": "en",
            "lang": "en"
        }
    ],
    "name": [
        {
            "value": "va.gov-modernization"
        }
    ],
    "created": [
        {
            "value": "2018-09-13T10:47:12+00:00",
            "format": "Y-m-d\\TH:i:sP"
        }
    ],
    "changed": [
        {
            "value": "2018-09-13T10:47:12+00:00",
            "lang": "en",
            "format": "Y-m-d\\TH:i:sP"
        }
    ],
    "default_langcode": [
        {
            "value": true,
            "lang": "en"
        }
    ]
}